Embedded VHDL LAB/full_adder/or_gate.vhdl
library IEEE;

use IEEE.STD_LOGIC_1164.ALL;

entity or_gate is

    port (

        a, b : in std_logic;

        y : out std_logic

    );

end or_gate;


architecture behavior of or_gate is

begin

    y <= a or b;

end behavior;

Embedded VHDL LAB/full_adder/half_adder.vhdl
library IEEE;

use IEEE.STD_LOGIC_1164.ALL;


entity half_adder is

    port (

        a, b : in std_logic;

        sum, carry : out std_logic

    );

end half_adder;


architecture behavior of half_adder is

begin

    process(a, b)

    begin

        sum <= a xor b;

        carry <= a and b;

    end process;

end behavior;

Embedded VHDL LAB/full_adder/full_adder.vhdl
library IEEE;

use IEEE.STD_LOGIC_1164.ALL;


entity full_adder is

    port (

        a, b, cin : in std_logic;

        sum, cout : out std_logic

    );

end full_adder;


architecture behavior of full_adder is

    component half_adder is

        port (

            a, b : in std_logic;

            sum, carry : out std_logic

        );

    end component;


    component or_gate is

        port (

            a, b : in std_logic;

            y : out std_logic

        );

    end component;



    signal s1, c1, c2 : std_logic; -- internal signals for intermediate results

begin

    w1: half_adder port map (a, b, s1, c1);

    w2: half_adder port map (s1, cin, sum, c2);

    w3: or_gate port map (c1, c2, cout);

end behavior;

full_adder/full_adder_tb.vhdl
library IEEE;

use IEEE.STD_LOGIC_1164.ALL;


entity full_adder_tb is

end full_adder_tb;


architecture test of full_adder_tb is

    signal a, b, cin, sum, cout: std_logic;



    component full_adder

        port (

            a, b, cin : in std_logic;

            sum, cout : out std_logic

        );

    end component;



begin

    UUT: full_adder port map (a => a, b => b, cin => cin, sum => sum, cout => cout);



    stimulus: process

    begin


        a <= '0'; b <= '0'; cin <= '0'; wait for  10 ns;

        a <= '0'; b <= '0'; cin <= '1'; wait for  10 ns;

        a <= '0'; b <= '1'; cin <= '0'; wait for  10 ns;

        a <= '0'; b <= '1'; cin <= '1'; wait for  10 ns;

        a <= '1'; b <= '0'; cin <= '0'; wait for  10 ns;

        a <= '1'; b <= '0'; cin <= '1'; wait for  10 ns;

        a <= '1'; b <= '1'; cin <= '0'; wait for  10 ns;

        a <= '1'; b <= '1'; cin <= '1'; wait for  10 ns;

        

        wait; -- Wait indefinitely

    end process stimulus;

end test;

full_adder/result.vcd
$date
  Sat Feb 10 23:50:46 2024
$end
$version
  GHDL v0
$end
$timescale
  1 fs
$end
$scope module standard $end
$upscope $end
$scope module std_logic_1164 $end
$upscope $end
$scope module full_adder_tb $end
$var reg 1 ! a $end
$var reg 1 " b $end
$var reg 1 # cin $end
$var reg 1 $ sum $end
$var reg 1 % cout $end
$scope module uut $end
$var reg 1 & a $end
$var reg 1 ' b $end
$var reg 1 ( cin $end
$var reg 1 ) sum $end
$var reg 1 * cout $end
$var reg 1 + s1 $end
$var reg 1 , c1 $end
$var reg 1 - c2 $end
$scope module w1 $end
$var reg 1 . a $end
$var reg 1 / b $end
$var reg 1 0 sum $end
$var reg 1 1 carry $end
$upscope $end
$scope module w2 $end
$var reg 1 2 a $end
$var reg 1 3 b $end
$var reg 1 4 sum $end
$var reg 1 5 carry $end
$upscope $end
$scope module w3 $end
$var reg 1 6 a $end
$var reg 1 7 b $end
$var reg 1 8 y $end
$upscope $end
$upscope $end
$upscope $end
$enddefinitions $end
#0
0!
0"
0#
0$
0%
0&
0'
0(
0)
0*
0+
0,
0-
0.
0/
00
01
02
03
04
05
06
07
08
#10000000
1#
1$
1(
1)
13
14
#20000000
1"
0#
1$
1'
0(
1)
1+
1/
10
12
03
14
#30000000
1#
0$
1%
1(
0)
1*
1-
13
04
15
17
18
#40000000
1!
0"
0#
1$
0%
1&
0'
0(
1)
0*
0-
1.
0/
03
14
05
07
08
#50000000
1#
0$
1%
1(
0)
1*
1-
13
04
15
17
18
#60000000
1"
0#
0$
1'
0(
0)
0+
1,
0-
1/
00
11
02
03
04
05
16
07
#70000000
1#
1$
1(
1)
13
14
